{
  "carousel": {
    "arrowContainer": {
      "arrows": [
        {
          "id": 1,
          "src": "arrow_left_white.svg",
          "alt": "White arrow left",
          "direction": "left"
        },
        {
          "id": 2,
          "src": "arrow_right_white.svg",
          "alt": "White arrow right",
          "direction": "right"
        }
      ],
      "counter": 0
    },
    "imageContainers": [
      {
        "id": 1,
        "isHidden": 0,
        "isTop": 1,
        "img": {
          "src": "carousel_img_1.png",
          "alt": "Delecious omlette"
        },
        "textBox": {
          "title": "made with love 1",
          "subTitle": "for you 1"
        }
      },
      {
        "id": 2,
        "isHidden": 1,
        "isTop": 1,
        "img": {
          "src": "carousel_img_2.png",
          "alt": "Captivating desert"
        },
        "textBox": {
          "title": "made with love 2",
          "subTitle": "for you 2"
        }
      },
      {
        "id": 3,
        "isHidden": 1,
        "isTop": 1,
        "img": {
          "src": "carousel_img_3.png",
          "alt": "Fragrant spices"
        },
        "textBox": {
          "title": "made with love 3",
          "subTitle": "for you 3"
        }
      }
    ]
  },  
  "about": {
    "title": "about",
    "subTitle": "we create delicious memories",
    "text": "Renome it is renowned restaurant delights the senses with elegant ambiance, gracious service and delectable menus in the heart of Manhattan’s. The distinctive setting boasts contemporary furnishings and finishes atop the restaurant’s grand modern architecture. Renome offers the room for private dining where guests enjoy creative foods and sumptuous late night desserts. Is one of the few Manhattan restaurants to have a coveted 3-star Michelin rating."
  },
  "gallery": {
    "title": "Gallery",
    "subTitle": "More about us via photos",
    "galleryImages": [
      {
        "path": "/assets/img/gallery_img_1.png"
      },
      {
        "path": "/assets/img/gallery_img_2.png"
      },
      {
        "path": "/assets/img/gallery_img_3.png"
      },
      {
        "path": "/assets/img/gallery_img_4.png"
      },
      {
        "path": "/assets/img/gallery_img_5.png"
      },
      {
        "path": "/assets/img/gallery_img_6.png"
      }
    ]
  }
}
